{"search_id":"98e7e04f-6f5a-26ec-c151-7022faf01b9b","user_id":1,"query_text":"Tempore molestiae occaecati.","filters":"Open Now","result_count":12,"clicked_product_id":"PRD-02533","timestamp":"2025-10-05 18:06:40.416"}
{"search_id":"520ddb9f-7296-5bb0-dcf2-e04612bed4d1","user_id":1,"query_text":"Quae reprehenderit consectetur similique.","filters":"Vegetarian","result_count":47,"clicked_product_id":"PRD-02533","timestamp":"2025-10-05 18:06:40.434"}
{"search_id":"80dd8db7-7600-cce6-76fb-97179b929d6b","user_id":3,"query_text":"Asperiores vel repellat autem reiciendis.","filters":"Deals","result_count":8,"clicked_product_id":"PRD-26830","timestamp":"2025-10-05 18:06:40.455"}
{"search_id":"22dc0abf-f97a-31f7-a2f3-a54bba3663d1","user_id":1,"query_text":"Et aut aut aut illum expedita iste.","filters":"Top Rated","result_count":47,"clicked_product_id":"PRD-26830","timestamp":"2025-10-05 18:06:40.479"}
{"search_id":"128e6ebf-b69f-9183-9cd0-7f29bd9a2f9c","user_id":5,"query_text":"Quas labore ut necessitatibus qui quis distinctio odio.","filters":"Vegetarian","result_count":36,"clicked_product_id":"PRD-02533","timestamp":"2025-10-05 18:06:40.490"}
{"search_id":"6279a94c-7a2a-e59c-c24c-c7f7afe29eb3","user_id":3,"query_text":"Eum sunt repudiandae ut qui voluptates harum.","filters":"Fast Delivery","result_count":0,"clicked_product_id":"PRD-26830","timestamp":"2025-10-05 18:06:40.509"}
{"search_id":"5d2d7350-1ded-de06-c77d-49240f0b14d4","user_id":8,"query_text":"At voluptatibus pariatur quae qui sit.","filters":"Vegetarian","result_count":31,"clicked_product_id":"PRD-61751","timestamp":"2025-10-05 18:06:40.521"}
{"search_id":"3f081cd3-54e4-be75-ba11-dd4e38b561d0","user_id":6,"query_text":"Cum nam non non dignissimos error accusamus.","filters":"Top Rated","result_count":16,"clicked_product_id":"PRD-02175","timestamp":"2025-10-05 18:06:40.544"}
{"search_id":"a133b4d4-fc29-0d6d-aa53-122173977813","user_id":6,"query_text":"Quam est dolorum cumque aut.","filters":"Vegetarian","result_count":42,"clicked_product_id":"PRD-02533","timestamp":"2025-10-05 18:06:40.554"}
{"search_id":"a4f84857-69ef-8a24-d3ff-7b827f4d66b6","user_id":5,"query_text":"Aliquid aliquam maxime repudiandae.","filters":"Top Rated","result_count":13,"clicked_product_id":"PRD-06804","timestamp":"2025-10-05 18:06:40.565"}
{"search_id":"b5c4e3b7-dadb-f14d-f393-f679ae96076c","user_id":6,"query_text":"Praesentium itaque occaecati ea est odio eum nihil.","filters":"Vegetarian","result_count":23,"clicked_product_id":"PRD-76390","timestamp":"2025-10-05 18:06:40.574"}
{"search_id":"64bc191f-3a73-1245-a359-22d90a6cb4f9","user_id":5,"query_text":"Ex incidunt voluptatum.","filters":"Fast Delivery","result_count":20,"clicked_product_id":"PRD-76390","timestamp":"2025-10-05 18:06:40.583"}
{"search_id":"bc34fed4-b824-e492-aad1-767a9204af64","user_id":1,"query_text":"Nemo cupiditate laborum voluptas.","filters":"Fast Delivery","result_count":26,"clicked_product_id":"PRD-02533","timestamp":"2025-10-05 18:06:40.593"}
{"search_id":"00e951ef-e7e6-0aae-a42f-53a543ed8649","user_id":5,"query_text":"Odit tempore consequatur ut ex.","filters":"Open Now","result_count":46,"clicked_product_id":"PRD-76390","timestamp":"2025-10-05 18:06:40.603"}
{"search_id":"0c7d4255-227f-9c64-ee56-10e97f978a0d","user_id":13,"query_text":"Necessitatibus impedit ea sed enim.","filters":"Deals","result_count":30,"clicked_product_id":"PRD-02533","timestamp":"2025-10-05 18:06:40.614"}
{"search_id":"8b720f2f-44b7-ae7a-b266-c068709e5241","user_id":12,"query_text":"Et ea ad dolorem modi vero saepe.","filters":"Fast Delivery","result_count":28,"clicked_product_id":"PRD-06804","timestamp":"2025-10-05 18:06:40.625"}
{"search_id":"6e131156-bc42-6086-aa33-b4792b35453b","user_id":18,"query_text":"Et rerum neque minus dolore quod.","filters":"Open Now","result_count":31,"clicked_product_id":"PRD-23338","timestamp":"2025-10-05 18:06:40.634"}
{"search_id":"89d9856f-bdf1-7472-c25d-1e0fa8096cb4","user_id":9,"query_text":"Impedit libero at beatae molestias.","filters":"Fast Delivery","result_count":47,"clicked_product_id":"PRD-84464","timestamp":"2025-10-05 18:06:40.647"}
{"search_id":"dc790525-f916-dde9-23f8-c8f3ee05737c","user_id":11,"query_text":"Ex dolores aspernatur quibusdam.","filters":"Fast Delivery","result_count":38,"clicked_product_id":"PRD-55406","timestamp":"2025-10-05 18:06:40.659"}
{"search_id":"d8499455-dc21-0b4a-7026-6e37ae03e16f","user_id":1,"query_text":"Sint nihil nam.","filters":"Top Rated","result_count":34,"clicked_product_id":"PRD-34428","timestamp":"2025-10-05 18:06:40.670"}
{"search_id":"425330ac-1c3e-8a0d-2aae-d0adb9ff1424","user_id":8,"query_text":"Maiores facere alias et nihil.","filters":"Fast Delivery","result_count":28,"clicked_product_id":"PRD-33148","timestamp":"2025-10-05 18:06:40.681"}
{"search_id":"a4bc86b4-302d-68c5-e719-d70c2d6d16fa","user_id":18,"query_text":"A quas aut quos sed.","filters":"Open Now","result_count":34,"clicked_product_id":"PRD-30932","timestamp":"2025-10-05 18:06:40.692"}
{"search_id":"a6db7753-dd06-018c-27e8-b9696c1683eb","user_id":2,"query_text":"Quis eaque expedita doloremque assumenda dolorum eos.","filters":"Vegetarian","result_count":4,"clicked_product_id":"PRD-18994","timestamp":"2025-10-05 18:06:40.702"}
{"search_id":"3f0a4d6e-dbda-0216-4f9e-94963956f1fa","user_id":6,"query_text":"Modi magni voluptatibus vel non voluptates est minus.","filters":"Top Rated","result_count":11,"clicked_product_id":"PRD-95547","timestamp":"2025-10-05 18:06:40.713"}
{"search_id":"39dff6d7-2308-0315-f8a2-d8919abe293e","user_id":20,"query_text":"Ducimus corporis aut.","filters":"Open Now","result_count":46,"clicked_product_id":"PRD-33148","timestamp":"2025-10-05 18:06:40.725"}
{"search_id":"958ecbc2-a7ea-9ec3-05c4-d5501ec9e49d","user_id":17,"query_text":"Explicabo architecto magnam veniam cum nulla totam.","filters":"Deals","result_count":20,"clicked_product_id":"PRD-06804","timestamp":"2025-10-05 18:06:40.737"}
{"search_id":"e71ffc34-de3a-1904-b328-8dbcaae2faef","user_id":10,"query_text":"Dolor molestiae recusandae velit facere.","filters":"Top Rated","result_count":24,"clicked_product_id":"PRD-74648","timestamp":"2025-10-05 18:06:40.748"}
{"search_id":"0cb17a68-0d79-5f96-8e39-68c5e461138b","user_id":15,"query_text":"Quibusdam quaerat et et.","filters":"Deals","result_count":31,"clicked_product_id":"PRD-95547","timestamp":"2025-10-05 18:06:40.759"}
{"search_id":"e2237a42-b397-7c19-ed27-6c6c37ddbbb2","user_id":29,"query_text":"Modi beatae consequuntur.","filters":"Deals","result_count":1,"clicked_product_id":"PRD-86501","timestamp":"2025-10-05 18:06:40.770"}
{"search_id":"05c75b41-6621-d2c5-2cf2-544ffa57dca2","user_id":4,"query_text":"Fugit aliquid fuga beatae voluptatibus debitis.","filters":"Top Rated","result_count":22,"clicked_product_id":"PRD-34420","timestamp":"2025-10-05 18:06:40.782"}
{"search_id":"550d944d-f95e-6edc-6f69-d9a6aa1a3ccd","user_id":27,"query_text":"Vero ipsum possimus magnam.","filters":"Top Rated","result_count":35,"clicked_product_id":"PRD-34428","timestamp":"2025-10-05 18:06:40.793"}
{"search_id":"1ab94ccb-9853-d2a0-3d62-38c7883558e4","user_id":1,"query_text":"Omnis labore explicabo voluptas corporis autem laudantium.","filters":"Fast Delivery","result_count":27,"clicked_product_id":"PRD-58957","timestamp":"2025-10-05 18:06:40.806"}
{"search_id":"47b4b64b-7b5a-a32d-c39c-c8c06254af23","user_id":1,"query_text":"Tenetur ullam hic autem aspernatur numquam autem.","filters":"Fast Delivery","result_count":9,"clicked_product_id":"PRD-24356","timestamp":"2025-10-05 18:06:40.819"}
{"search_id":"7ad367e5-3512-3847-fa83-78dbcc7f7e97","user_id":33,"query_text":"Quisquam tempore vitae.","filters":"Deals","result_count":28,"clicked_product_id":"PRD-06804","timestamp":"2025-10-05 18:06:40.833"}
{"search_id":"c85e6053-e810-fa5d-51cf-6319dd417291","user_id":24,"query_text":"Et veniam quis quia illo repellendus iure molestiae.","filters":"Deals","result_count":22,"clicked_product_id":"PRD-06804","timestamp":"2025-10-05 18:06:40.843"}
{"search_id":"f91e4a7a-f43d-c33a-8c59-8aa7f4d896e0","user_id":33,"query_text":"Eos ipsum fugit alias.","filters":"Fast Delivery","result_count":26,"clicked_product_id":"PRD-24356","timestamp":"2025-10-05 18:06:40.854"}
{"search_id":"c08b6401-28f1-e1e3-0199-c4f9b4d291bf","user_id":29,"query_text":"Sed molestiae rem exercitationem qui.","filters":"Open Now","result_count":28,"clicked_product_id":"PRD-15012","timestamp":"2025-10-05 18:06:40.864"}
{"search_id":"a8d65957-c0b7-ade5-081c-be1f9c614354","user_id":12,"query_text":"Inventore aut rerum qui fugiat voluptatibus est.","filters":"Deals","result_count":18,"clicked_product_id":"PRD-34428","timestamp":"2025-10-05 18:06:40.875"}
{"search_id":"c776f6ef-1934-0d7b-63de-2fc49c61968c","user_id":21,"query_text":"Reprehenderit ullam quo maiores aspernatur quos vel labore.","filters":"Top Rated","result_count":5,"clicked_product_id":"PRD-27130","timestamp":"2025-10-05 18:06:40.885"}
{"search_id":"64bff820-08c9-82b7-6b7c-6b28631ecfe8","user_id":27,"query_text":"Et excepturi doloribus odit sit.","filters":"Top Rated","result_count":37,"clicked_product_id":"PRD-04746","timestamp":"2025-10-05 18:06:40.895"}
{"search_id":"4f17a4b9-e8d5-b9ac-c779-85d14e7750b4","user_id":33,"query_text":"Nihil quam a.","filters":"Fast Delivery","result_count":31,"clicked_product_id":"PRD-06605","timestamp":"2025-10-05 18:06:40.905"}
{"search_id":"939f1131-93f6-e48a-e64f-6fcc40595db1","user_id":6,"query_text":"Ut eos voluptatem eos corporis illo aperiam.","filters":"Open Now","result_count":33,"clicked_product_id":"PRD-42993","timestamp":"2025-10-05 18:06:40.915"}
{"search_id":"57fe6441-9c58-866f-abb6-0a8649b706b8","user_id":44,"query_text":"Delectus molestias voluptatem labore eveniet eos non recusandae.","filters":"Open Now","result_count":7,"clicked_product_id":"PRD-34210","timestamp":"2025-10-05 18:06:40.924"}
{"search_id":"35c86c1c-3995-9157-ef10-34f58bcc9436","user_id":37,"query_text":"Aut libero sapiente aliquam.","filters":"Open Now","result_count":46,"clicked_product_id":"PRD-24356","timestamp":"2025-10-05 18:06:40.934"}
{"search_id":"0ddb756f-5486-e74e-734f-5d05dbbf7cbf","user_id":25,"query_text":"Quia et nemo cum unde deserunt.","filters":"Open Now","result_count":49,"clicked_product_id":"PRD-34210","timestamp":"2025-10-05 18:06:40.948"}
{"search_id":"ec63d7ee-2680-bdae-13ca-a5a05197e750","user_id":7,"query_text":"Quis autem consequatur est dicta est.","filters":"Deals","result_count":47,"clicked_product_id":"PRD-89877","timestamp":"2025-10-05 18:06:40.959"}
{"search_id":"e0480b8d-2dfb-35f0-5af3-9d5233a27167","user_id":20,"query_text":"Quidem magnam vel.","filters":"Fast Delivery","result_count":35,"clicked_product_id":"PRD-86501","timestamp":"2025-10-05 18:06:40.969"}
{"search_id":"4e0a2499-ce17-e8f8-8d41-45df7999ccd5","user_id":11,"query_text":"Voluptas voluptatem illo.","filters":"Fast Delivery","result_count":12,"clicked_product_id":"PRD-26830","timestamp":"2025-10-05 18:06:40.979"}
{"search_id":"6a541175-66f0-01c3-8b6d-8c7cbc163e1d","user_id":5,"query_text":"Molestiae magnam qui odio excepturi.","filters":"Vegetarian","result_count":1,"clicked_product_id":"PRD-02175","timestamp":"2025-10-05 18:06:40.990"}
{"search_id":"1adb7b6f-98e0-3530-d38f-41d34b5440a6","user_id":39,"query_text":"Sit sit qui necessitatibus eaque quo.","filters":"Vegetarian","result_count":45,"clicked_product_id":"PRD-28994","timestamp":"2025-10-05 18:06:41.000"}
{"search_id":"459353ce-e3f3-5fe4-2f0a-7b6ee56d7a03","user_id":5,"query_text":"Non aut officia enim qui numquam unde aut.","filters":"Deals","result_count":44,"clicked_product_id":"PRD-30932","timestamp":"2025-10-05 18:06:41.010"}
{"search_id":"89222050-9f7f-99ab-a81a-f93c01cd482d","user_id":1,"query_text":"Quas numquam est et ut voluptas.","filters":"Deals","result_count":25,"clicked_product_id":"PRD-23338","timestamp":"2025-10-05 18:06:41.024"}
{"search_id":"a9c1bba3-a54d-c2dc-6efb-590f32d936d3","user_id":13,"query_text":"Repellat quia sed.","filters":"Top Rated","result_count":19,"clicked_product_id":"PRD-98908","timestamp":"2025-10-05 18:06:41.035"}
{"search_id":"771a8baf-1b58-edc8-d0ba-59fc08fcf2c6","user_id":5,"query_text":"Qui ut et odio cupiditate nesciunt.","filters":"Deals","result_count":17,"clicked_product_id":"PRD-24356","timestamp":"2025-10-05 18:06:41.046"}
{"search_id":"7c854214-bb11-df0b-bf1e-08e823968e33","user_id":28,"query_text":"Omnis aliquam esse voluptatum quod quis ex quibusdam.","filters":"Top Rated","result_count":18,"clicked_product_id":"PRD-23338","timestamp":"2025-10-05 18:06:41.056"}
{"search_id":"982c1997-4648-7ba8-e462-c7c20c989b91","user_id":16,"query_text":"Et ut sit et alias architecto.","filters":"Open Now","result_count":46,"clicked_product_id":"PRD-15012","timestamp":"2025-10-05 18:06:41.066"}
{"search_id":"1160a7c0-9f74-53e3-eaae-307c5f095834","user_id":29,"query_text":"Sed sapiente quia distinctio magnam aut.","filters":"Deals","result_count":5,"clicked_product_id":"PRD-38212","timestamp":"2025-10-05 18:06:41.076"}
{"search_id":"458d6502-b37b-3085-b27d-4afeff3e56e5","user_id":12,"query_text":"Consectetur qui est sed doloremque ipsa.","filters":"Top Rated","result_count":22,"clicked_product_id":"PRD-95153","timestamp":"2025-10-05 18:06:41.087"}
{"search_id":"2a9b7ffe-b89a-2788-f0f8-c71bcf42b03f","user_id":19,"query_text":"Amet praesentium blanditiis cumque quod architecto.","filters":"Open Now","result_count":19,"clicked_product_id":"PRD-96588","timestamp":"2025-10-05 18:06:41.097"}
{"search_id":"efe6c321-6188-8c9b-3cd0-d88d3fb67835","user_id":42,"query_text":"Est non aut illum ipsa consequatur cumque accusamus.","filters":"Vegetarian","result_count":41,"clicked_product_id":"PRD-38212","timestamp":"2025-10-05 18:06:41.108"}
{"search_id":"0321416c-c17a-11ca-2139-717551a4df26","user_id":6,"query_text":"Quaerat et saepe.","filters":"Top Rated","result_count":37,"clicked_product_id":"PRD-95448","timestamp":"2025-10-05 18:06:41.118"}
{"search_id":"c53901f8-2551-3a12-0d7d-f01a212b3f61","user_id":10,"query_text":"Officia earum atque dolores.","filters":"Deals","result_count":48,"clicked_product_id":"PRD-48904","timestamp":"2025-10-05 18:06:41.130"}
{"search_id":"724a3042-b6ab-b7e2-2f54-f2a772bf8822","user_id":52,"query_text":"Ipsam accusantium aspernatur excepturi impedit totam vitae.","filters":"Top Rated","result_count":10,"clicked_product_id":"PRD-98908","timestamp":"2025-10-05 18:06:41.143"}
{"search_id":"865fae12-7f57-6e9c-469c-f14df42230bd","user_id":14,"query_text":"Nemo libero consequuntur molestiae magnam voluptates eaque vitae.","filters":"Fast Delivery","result_count":37,"clicked_product_id":"PRD-55406","timestamp":"2025-10-05 18:06:41.154"}
{"search_id":"a8d6b12f-92c5-7bac-ac48-f73344a4abc2","user_id":42,"query_text":"Vitae aut quaerat ea dicta.","filters":"Vegetarian","result_count":34,"clicked_product_id":"PRD-06804","timestamp":"2025-10-05 18:06:41.164"}
{"search_id":"75506695-961b-6962-ebda-1b402631128f","user_id":45,"query_text":"Velit id commodi dolores sequi possimus consequatur.","filters":"Open Now","result_count":16,"clicked_product_id":"PRD-06605","timestamp":"2025-10-05 18:06:41.175"}
{"search_id":"9cee4ffb-346b-c3b5-21af-1c569b801953","user_id":58,"query_text":"Nemo animi possimus est.","filters":"Top Rated","result_count":33,"clicked_product_id":"PRD-13898","timestamp":"2025-10-05 18:06:41.187"}
{"search_id":"b4aca11e-be65-0a26-c93b-7c7a7c8ff09b","user_id":40,"query_text":"Itaque in praesentium asperiores dolores.","filters":"Deals","result_count":44,"clicked_product_id":"PRD-36780","timestamp":"2025-10-05 18:06:41.199"}
{"search_id":"0fe8c34f-52d4-1c90-3c70-f7d68b882861","user_id":18,"query_text":"Blanditiis placeat maiores quas distinctio totam quo eos.","filters":"Vegetarian","result_count":15,"clicked_product_id":"PRD-02533","timestamp":"2025-10-05 18:06:41.211"}
{"search_id":"14d71564-c42c-de40-dd32-4c496731dd4d","user_id":23,"query_text":"Consequatur corrupti veniam expedita numquam atque labore voluptatem.","filters":"Vegetarian","result_count":12,"clicked_product_id":"PRD-02533","timestamp":"2025-10-05 18:06:41.229"}
{"search_id":"9b0598e1-84cc-8636-304a-2795b9875cf3","user_id":24,"query_text":"Qui asperiores dolor.","filters":"Open Now","result_count":48,"clicked_product_id":"PRD-34428","timestamp":"2025-10-05 18:06:41.241"}
{"search_id":"8aa57a1d-040d-8199-52c8-c0be79b2f70d","user_id":70,"query_text":"Accusamus suscipit sint.","filters":"Top Rated","result_count":10,"clicked_product_id":"PRD-12082","timestamp":"2025-10-05 18:06:41.257"}
{"search_id":"ba227577-3aa7-5a79-23e1-988d5b7e2e12","user_id":50,"query_text":"Suscipit vel cumque.","filters":"Fast Delivery","result_count":33,"clicked_product_id":"PRD-98908","timestamp":"2025-10-05 18:06:41.269"}
{"search_id":"c7588bf2-ff1c-dd3f-06cb-2ef396d1f413","user_id":62,"query_text":"Sit qui quisquam.","filters":"Deals","result_count":22,"clicked_product_id":"PRD-79145","timestamp":"2025-10-05 18:06:41.281"}
{"search_id":"98786e38-c204-ff18-94af-51246c933f1c","user_id":49,"query_text":"Ad fugit sint cum blanditiis eum adipisci.","filters":"Open Now","result_count":46,"clicked_product_id":"PRD-41433","timestamp":"2025-10-05 18:06:41.292"}
{"search_id":"fe6183cf-aa95-defa-1630-74f978734f1c","user_id":56,"query_text":"Qui sunt quo dolorem unde.","filters":"Deals","result_count":14,"clicked_product_id":"PRD-29510","timestamp":"2025-10-05 18:06:41.303"}
{"search_id":"91256926-205e-b257-b722-bb796b59d1bb","user_id":60,"query_text":"Eius excepturi atque aut expedita est et.","filters":"Deals","result_count":27,"clicked_product_id":"PRD-84464","timestamp":"2025-10-05 18:06:41.315"}
{"search_id":"d0e36852-189e-714c-d07c-85017401e0f7","user_id":36,"query_text":"Libero atque voluptatum necessitatibus quo dicta veniam nihil.","filters":"Top Rated","result_count":1,"clicked_product_id":"PRD-23338","timestamp":"2025-10-05 18:06:41.327"}
{"search_id":"a39294f9-3b83-0594-c327-351c87fd20d2","user_id":78,"query_text":"Provident similique quod dignissimos repellat sapiente.","filters":"Vegetarian","result_count":16,"clicked_product_id":"PRD-27038","timestamp":"2025-10-05 18:06:41.340"}
{"search_id":"d6fd86b1-7a23-7d50-b048-ca9ad20de1ee","user_id":40,"query_text":"Odit id rem sed qui aperiam architecto adipisci.","filters":"Vegetarian","result_count":25,"clicked_product_id":"PRD-34246","timestamp":"2025-10-05 18:06:41.351"}
{"search_id":"9f44cd7b-ed5a-edfc-2722-2cd4381ff4a6","user_id":10,"query_text":"Quia fugit reiciendis.","filters":"Deals","result_count":2,"clicked_product_id":"PRD-61322","timestamp":"2025-10-05 18:06:41.362"}
{"search_id":"60c83375-e337-77ff-90fd-1e98f619d686","user_id":18,"query_text":"Quia hic sit accusamus et aspernatur.","filters":"Top Rated","result_count":18,"clicked_product_id":"PRD-56616","timestamp":"2025-10-05 18:06:41.373"}
{"search_id":"4a317c7d-acc0-3a76-d9d0-68f3a87c6eb9","user_id":17,"query_text":"Atque quas officiis deserunt porro minus.","filters":"Deals","result_count":39,"clicked_product_id":"PRD-29510","timestamp":"2025-10-05 18:06:41.384"}
{"search_id":"94e2b822-0b73-1493-1ca5-4ec6df4cd994","user_id":1,"query_text":"Repellendus aperiam possimus illo sint nihil repudiandae.","filters":"Fast Delivery","result_count":19,"clicked_product_id":"PRD-01466","timestamp":"2025-10-05 18:06:41.396"}
{"search_id":"4b70f4bb-dffd-249c-9268-69cae36f1ab8","user_id":9,"query_text":"Consequatur veritatis natus porro.","filters":"Top Rated","result_count":15,"clicked_product_id":"PRD-43409","timestamp":"2025-10-05 18:06:41.407"}
{"search_id":"36d6e8c1-7566-857d-9dba-c6dcc7593a80","user_id":67,"query_text":"Ut cumque voluptas.","filters":"Vegetarian","result_count":49,"clicked_product_id":"PRD-30932","timestamp":"2025-10-05 18:06:41.419"}
{"search_id":"fde9b748-6885-f736-2038-cc95ab282733","user_id":69,"query_text":"Voluptates eaque odio magni assumenda tempora voluptates accusamus.","filters":"Open Now","result_count":28,"clicked_product_id":"PRD-67552","timestamp":"2025-10-05 18:06:41.430"}
{"search_id":"4ef5fefc-8a19-1f88-9f12-58b2c66e2fc2","user_id":26,"query_text":"Dolores laudantium sit.","filters":"Vegetarian","result_count":44,"clicked_product_id":"PRD-55406","timestamp":"2025-10-05 18:06:41.441"}
{"search_id":"e0b5fee1-f675-9339-8a63-9c334324b39a","user_id":42,"query_text":"Fugit in ipsa.","filters":"Top Rated","result_count":1,"clicked_product_id":"PRD-74648","timestamp":"2025-10-05 18:06:41.456"}
{"search_id":"5234e91e-a6f2-ab44-29cc-57bbdeb363eb","user_id":27,"query_text":"Neque voluptatem pariatur.","filters":"Open Now","result_count":14,"clicked_product_id":"PRD-18994","timestamp":"2025-10-05 18:06:41.471"}
{"search_id":"ddf04d75-a5b1-19ee-ad87-ece28fef336a","user_id":6,"query_text":"Adipisci repellendus nesciunt.","filters":"Fast Delivery","result_count":13,"clicked_product_id":"PRD-34210","timestamp":"2025-10-05 18:06:41.484"}
{"search_id":"3ec5297a-ddc8-d7ba-ad55-b95965302d94","user_id":92,"query_text":"Veritatis eum sit ea exercitationem nihil deserunt.","filters":"Open Now","result_count":43,"clicked_product_id":"PRD-68920","timestamp":"2025-10-05 18:06:41.497"}
{"search_id":"2f8e9f63-bf40-a0aa-b511-c2f6853b57fb","user_id":45,"query_text":"Aut laboriosam ullam sunt accusantium.","filters":"Deals","result_count":33,"clicked_product_id":"PRD-04136","timestamp":"2025-10-05 18:06:41.510"}
{"search_id":"1dee5352-321d-5961-6780-a127a5139c08","user_id":56,"query_text":"Veniam et magnam ut fugiat repellendus non.","filters":"Top Rated","result_count":41,"clicked_product_id":"PRD-30932","timestamp":"2025-10-05 18:06:41.525"}
{"search_id":"f7934cd9-dbe5-b703-5377-e369791a9579","user_id":15,"query_text":"Pariatur necessitatibus consequatur placeat et optio doloremque et.","filters":"Top Rated","result_count":32,"clicked_product_id":"PRD-03687","timestamp":"2025-10-05 18:06:41.538"}
{"search_id":"b7a338d3-4c9e-eb95-9e94-630ce2f170c2","user_id":18,"query_text":"Facere totam ut vel velit eos.","filters":"Top Rated","result_count":19,"clicked_product_id":"PRD-27130","timestamp":"2025-10-05 18:06:41.554"}
{"search_id":"d92e56b8-fef0-6d6b-7c27-ef23c32c30e2","user_id":14,"query_text":"Aut dolores officiis.","filters":"Top Rated","result_count":32,"clicked_product_id":"PRD-69563","timestamp":"2025-10-05 18:06:41.574"}
{"search_id":"13baed1a-8bde-1a29-d7c9-270a863d8a66","user_id":10,"query_text":"Quas soluta illum dolores sit sint.","filters":"Vegetarian","result_count":33,"clicked_product_id":"PRD-65934","timestamp":"2025-10-05 18:06:41.593"}
{"search_id":"8a3ce519-03ec-7184-21f8-2b6fee985529","user_id":42,"query_text":"Ducimus facilis officiis aut quis.","filters":"Open Now","result_count":26,"clicked_product_id":"PRD-77275","timestamp":"2025-10-05 18:06:41.610"}
{"search_id":"48ec3da5-c88b-6ed8-4f2d-462dd2e2d61d","user_id":80,"query_text":"Atque ipsum sapiente molestiae rem illum.","filters":"Deals","result_count":18,"clicked_product_id":"PRD-21760","timestamp":"2025-10-05 18:06:41.629"}
{"search_id":"3b4581f6-71ee-de01-e85d-6c14d97e50e5","user_id":26,"query_text":"Ipsa dolore facilis sit sit porro corrupti.","filters":"Deals","result_count":30,"clicked_product_id":"PRD-04746","timestamp":"2025-10-05 18:06:41.644"}
{"search_id":"11003230-8914-9a6d-20ad-70e92bad1d34","user_id":47,"query_text":"Quaerat id deleniti dolores repellat.","filters":"Fast Delivery","result_count":7,"clicked_product_id":"PRD-86270","timestamp":"2025-10-05 18:06:41.660"}
{"search_id":"6b58e825-6c3c-bddd-7971-fcc3f73cc683","user_id":67,"query_text":"Est ut veniam corporis dolorem libero aliquam.","filters":"Vegetarian","result_count":33,"clicked_product_id":"PRD-56690","timestamp":"2025-10-05 18:06:41.677"}
{"search_id":"b8ed7084-f54b-0571-c6c3-00d88b866aaa","user_id":10,"query_text":"Nulla non impedit expedita repellendus.","filters":"Deals","result_count":21,"clicked_product_id":"PRD-34246","timestamp":"2025-10-05 18:06:41.694"}
{"search_id":"e0cadf94-edf8-cd43-d104-fd10a0927b13","user_id":52,"query_text":"Suscipit optio eius ut.","filters":"Fast Delivery","result_count":14,"clicked_product_id":"PRD-27038","timestamp":"2025-10-05 18:06:41.711"}
{"search_id":"961d4b38-33ef-8115-58e1-84080e643648","user_id":80,"query_text":"Et repellendus dignissimos nulla.","filters":"Top Rated","result_count":0,"clicked_product_id":"PRD-12082","timestamp":"2025-10-05 18:06:41.726"}
{"search_id":"c578dd03-48ee-90c0-f40d-b734fefd1aee","user_id":98,"query_text":"Rerum totam possimus vero quasi tempora recusandae.","filters":"Top Rated","result_count":2,"clicked_product_id":"PRD-90527","timestamp":"2025-10-05 18:06:41.742"}
{"search_id":"6ef5c332-27e1-461a-06f2-91c79fe23a38","user_id":102,"query_text":"Blanditiis voluptates numquam.","filters":"Open Now","result_count":1,"clicked_product_id":"PRD-74648","timestamp":"2025-10-05 18:06:41.758"}
{"search_id":"760ff297-cfef-6e5f-1820-f36b070afab1","user_id":83,"query_text":"Animi aliquam sapiente explicabo.","filters":"Top Rated","result_count":17,"clicked_product_id":"PRD-45405","timestamp":"2025-10-05 18:06:41.774"}
{"search_id":"12cfa30a-f508-4fb4-daf3-b4abfc157b8b","user_id":100,"query_text":"Perferendis expedita itaque.","filters":"Fast Delivery","result_count":28,"clicked_product_id":"PRD-65222","timestamp":"2025-10-05 18:06:41.789"}
{"search_id":"4fb5a00c-3e51-328f-601d-0334a7b778b1","user_id":11,"query_text":"Rem et omnis maxime dolores deserunt.","filters":"Top Rated","result_count":44,"clicked_product_id":"PRD-01466","timestamp":"2025-10-05 18:06:41.804"}
{"search_id":"a2b204fb-c6d7-6781-359b-77a1d1674910","user_id":51,"query_text":"Aut sunt nobis sit est.","filters":"Vegetarian","result_count":8,"clicked_product_id":"PRD-96083","timestamp":"2025-10-05 18:06:41.831"}
{"search_id":"0cadd285-1ead-a6c9-e586-328849f96f2f","user_id":11,"query_text":"Ut ea accusantium eius.","filters":"Top Rated","result_count":19,"clicked_product_id":"PRD-12082","timestamp":"2025-10-05 18:06:41.843"}
{"search_id":"1c01f4ef-0f3f-dfe2-2237-b225e610e8bf","user_id":5,"query_text":"In quibusdam qui consequatur dolore sint sit.","filters":"Open Now","result_count":24,"clicked_product_id":"PRD-67552","timestamp":"2025-10-05 18:06:41.855"}
{"search_id":"5c24ca15-c5c1-efde-6a2c-6916bdff9f5d","user_id":23,"query_text":"Dolor quos eos velit quia nesciunt aut.","filters":"Fast Delivery","result_count":26,"clicked_product_id":"PRD-68920","timestamp":"2025-10-05 18:06:41.868"}
{"search_id":"a037a957-99cd-db92-4790-b9b997191a80","user_id":96,"query_text":"Illum et omnis ut.","filters":"Top Rated","result_count":4,"clicked_product_id":"PRD-67510","timestamp":"2025-10-05 18:06:41.881"}
{"search_id":"854013f0-427e-c292-9dbd-c7468e134bd4","user_id":68,"query_text":"Excepturi non aut ut pariatur reiciendis.","filters":"Deals","result_count":29,"clicked_product_id":"PRD-12082","timestamp":"2025-10-05 18:06:41.894"}
{"search_id":"2e4138f6-2e90-bfa9-2883-d6a87543d098","user_id":93,"query_text":"Qui facilis perspiciatis sed.","filters":"Deals","result_count":23,"clicked_product_id":"PRD-56616","timestamp":"2025-10-05 18:06:41.907"}
{"search_id":"0a6d56ca-a992-9116-4721-2be028f8436c","user_id":46,"query_text":"Voluptatum iusto facere est.","filters":"Fast Delivery","result_count":45,"clicked_product_id":"PRD-47045","timestamp":"2025-10-05 18:06:41.919"}
{"search_id":"f347a25e-b662-2cfd-f255-4a2d9bdcffb4","user_id":42,"query_text":"Non nobis et a enim explicabo.","filters":"Deals","result_count":29,"clicked_product_id":"PRD-21760","timestamp":"2025-10-05 18:06:41.933"}
{"search_id":"2a028e24-1403-8b59-86a8-eff1f594d472","user_id":95,"query_text":"Alias aspernatur deleniti perferendis quasi.","filters":"Vegetarian","result_count":28,"clicked_product_id":"PRD-32788","timestamp":"2025-10-05 18:06:41.946"}
{"search_id":"64356f24-2cfa-a664-7494-7cadc39315af","user_id":4,"query_text":"Ut vitae fugit optio cum saepe.","filters":"Deals","result_count":9,"clicked_product_id":"PRD-02533","timestamp":"2025-10-05 18:06:41.960"}
{"search_id":"18020a2c-44ca-1d11-a29e-9633ce787289","user_id":28,"query_text":"Iusto ea voluptas consequatur impedit sed voluptatem iste.","filters":"Open Now","result_count":1,"clicked_product_id":"PRD-20404","timestamp":"2025-10-05 18:06:41.974"}
{"search_id":"362be5c3-ac4d-c925-3587-08c5d00abc1c","user_id":69,"query_text":"Iure repudiandae ea inventore quaerat et.","filters":"Open Now","result_count":8,"clicked_product_id":"PRD-50193","timestamp":"2025-10-05 18:06:41.987"}
{"search_id":"4b6cabfa-cf7d-d627-2543-ff3b09db2b76","user_id":63,"query_text":"Molestiae est officiis velit.","filters":"Top Rated","result_count":20,"clicked_product_id":"PRD-34428","timestamp":"2025-10-05 18:06:42.000"}
{"search_id":"3e22d2d7-faab-25b8-a926-81d1e7b424dc","user_id":16,"query_text":"Nobis nemo adipisci non nihil quasi non.","filters":"Top Rated","result_count":13,"clicked_product_id":"PRD-32788","timestamp":"2025-10-05 18:06:42.013"}
{"search_id":"2857399e-7839-9cf3-f74b-899045c9b4b5","user_id":88,"query_text":"Repellat fugiat iure atque qui.","filters":"Fast Delivery","result_count":16,"clicked_product_id":"PRD-27130","timestamp":"2025-10-05 18:06:42.028"}
{"search_id":"5fc7fd92-4f1c-c503-4f09-fd80083db790","user_id":127,"query_text":"Consequatur ut corporis reprehenderit tempora.","filters":"Fast Delivery","result_count":24,"clicked_product_id":"PRD-39270","timestamp":"2025-10-05 18:06:42.043"}
{"search_id":"5219d522-1c29-8153-58aa-52274cc175a3","user_id":73,"query_text":"Est veniam dolorem cumque ut et nobis cupiditate.","filters":"Fast Delivery","result_count":49,"clicked_product_id":"PRD-65934","timestamp":"2025-10-05 18:06:42.056"}
{"search_id":"ef96d428-9514-b272-6569-3abfc2fb582a","user_id":21,"query_text":"Assumenda non vitae eaque sit.","filters":"Open Now","result_count":33,"clicked_product_id":"PRD-34428","timestamp":"2025-10-05 18:06:42.072"}
{"search_id":"54a97bfe-ab0a-e7e8-262c-bf51bb5f718e","user_id":68,"query_text":"Quibusdam consequatur at.","filters":"Open Now","result_count":4,"clicked_product_id":"PRD-54828","timestamp":"2025-10-05 18:06:42.095"}
{"search_id":"bb258a89-bf6a-2e29-4c2b-39bc2544a6af","user_id":17,"query_text":"Similique ipsum reiciendis nobis.","filters":"Deals","result_count":25,"clicked_product_id":"PRD-71011","timestamp":"2025-10-05 18:06:42.115"}
{"search_id":"3f8fdf19-cace-d116-1e8b-8ea6b526bf25","user_id":103,"query_text":"Quos hic doloribus molestiae quis vero.","filters":"Fast Delivery","result_count":12,"clicked_product_id":"PRD-97682","timestamp":"2025-10-05 18:06:42.132"}
{"search_id":"d640a8b3-de33-361a-aa96-5a20d5cbbd7f","user_id":53,"query_text":"Fuga eum velit sapiente.","filters":"Top Rated","result_count":7,"clicked_product_id":"PRD-09631","timestamp":"2025-10-05 18:06:42.147"}
{"search_id":"f064473d-9096-af95-44be-8a33b49b6887","user_id":49,"query_text":"Error aut sit ut cum unde optio.","filters":"Top Rated","result_count":12,"clicked_product_id":"PRD-82274","timestamp":"2025-10-05 18:06:42.164"}
{"search_id":"de7adde1-694d-81b7-4ae7-5cd3b6f192c0","user_id":116,"query_text":"Ut deleniti voluptatibus dolores autem distinctio rerum consequatur.","filters":"Deals","result_count":33,"clicked_product_id":"PRD-48181","timestamp":"2025-10-05 18:06:42.180"}
